[{"player_id": 669743, "player_name": "Alex Call", "position": "LF", "team_id": 119, "team": "LAD", "status": "A"}, {"player_id": 690976, "player_name": "Alex Freeland", "position": "2B", "team_id": 119, "team": "LAD", "status": "A"}, {"player_id": 681911, "player_name": "Alex Vesia", "position": "P", "team_id": 119, "team": "LAD", "status": "A"}, {"player_id": 681624, "player_name": "Andy Pages", "position": "CF", "team_id": 119, "team": "LAD", "status": "A"}, {"player_id": 595014, "player_name": "Blake Treinen", "position": "P", "team_id": 119, "team": "LAD", "status": "A"}, {"player_id": 687221, "player_name": "Dalton Rushing", "position": "C", "team_id": 119, "team": "LAD", "status": "A"}, {"player_id": 683618, "player_name": "Edgardo Henriquez", "position": "P", "team_id": 119, "team": "LAD", "status": "A"}, {"player_id": 686218, "player_name": "Emmet Sheehan", "position": "P", "team_id": 119, "team": "LAD", "status": "A"}, {"player_id": 518692, "player_name": "Freddie Freeman", "position": "1B", "team_id": 119, "team": "LAD", "status": "A"}, {"player_id": 808975, "player_name": "Hyeseong Kim", "position": "SS", "team_id": 119, "team": "LAD", "status": "A"}, {"player_id": 676263, "player_name": "Jack Dreyer", "position": "P", "team_id": 119, "team": "LAD", "status": "A"}, {"player_id": 671109, "player_name": "Jake Eder", "position": "P", "team_id": 119, "team": "LAD", "status": "A"}, {"player_id": 680736, "player_name": "Justin Wrobleski", "position": "P", "team_id": 119, "team": "LAD", "status": "A"}, {"player_id": 669165, "player_name": "Kyle Hurt", "position": "P", "team_id": 119, "team": "LAD", "status": "A"}, {"player_id": 663656, "player_name": "Kyle Tucker", "position": "RF", "team_id": 119, "team": "LAD", "status": "A"}, {"player_id": 571970, "player_name": "Max Muncy", "position": "3B", "team_id": 119, "team": "LAD", "status": "A"}, {"player_id": 500743, "player_name": "Miguel Rojas", "position": "SS", "team_id": 119, "team": "LAD", "status": "A"}, {"player_id": 808963, "player_name": "Roki Sasaki", "position": "P", "team_id": 119, "team": "LAD", "status": "A"}, {"player_id": 669289, "player_name": "Santiago Espinal", "position": "3B", "team_id": 119, "team": "LAD", "status": "A"}, {"player_id": 660271, "player_name": "Shohei Ohtani", "position": "TWP", "team_id": 119, "team": "LAD", "status": "A"}, {"player_id": 656945, "player_name": "Tanner Scott", "position": "P", "team_id": 119, "team": "LAD", "status": "A"}, {"player_id": 606192, "player_name": "Teoscar Hern\u00e1ndez", "position": "LF", "team_id": 119, "team": "LAD", "status": "A"}, {"player_id": 607192, "player_name": "Tyler Glasnow", "position": "P", "team_id": 119, "team": "LAD", "status": "A"}, {"player_id": 694361, "player_name": "Will Klein", "position": "P", "team_id": 119, "team": "LAD", "status": "A"}, {"player_id": 669257, "player_name": "Will Smith", "position": "C", "team_id": 119, "team": "LAD", "status": "A"}, {"player_id": 808967, "player_name": "Yoshinobu Yamamoto", "position": "P", "team_id": 119, "team": "LAD", "status": "A"}]