[{"player_id": 607625, "game_date": "2026-03-29", "team": "", "era": 0.0, "whip": 0.79, "k9": 4.26}, {"player_id": 607625, "game_date": "2026-04-04", "team": "", "era": 1.59, "whip": 0.97, "k9": 12.6}, {"player_id": 607625, "game_date": "2026-04-09", "team": "", "era": 1.53, "whip": 1.08, "k9": 5.68}, {"player_id": 607625, "game_date": "2026-04-15", "team": "", "era": 1.48, "whip": 0.99, "k9": 9.45}, {"player_id": 607625, "game_date": "2026-04-20", "team": "", "era": 1.15, "whip": 0.93, "k9": 9.0}, {"player_id": 607625, "game_date": "2026-04-26", "team": "", "era": 2.63, "whip": 1.17, "k9": 4.26}]