[{"player_id": 668670, "game_date": "2026-03-28", "team": "", "opponent": "", "home_away": false, "ab": 3, "hits": 0, "doubles": 0, "triples": 0, "hr": 0, "rbi": 0, "runs": 0, "bb": 0, "k": 1, "sb": 0, "tb": 0, "avg": 0.0, "obp": 0.0, "slg": 0.0, "hit_flag": 0, "hr_flag": 0}, {"player_id": 668670, "game_date": "2026-03-31", "team": "", "opponent": "", "home_away": false, "ab": 3, "hits": 1, "doubles": 1, "triples": 0, "hr": 0, "rbi": 1, "runs": 1, "bb": 0, "k": 1, "sb": 0, "tb": 2, "avg": 0.167, "obp": 0.167, "slg": 0.333, "hit_flag": 1, "hr_flag": 0}, {"player_id": 668670, "game_date": "2026-04-06", "team": "", "opponent": "", "home_away": false, "ab": 4, "hits": 0, "doubles": 0, "triples": 0, "hr": 0, "rbi": 0, "runs": 0, "bb": 0, "k": 2, "sb": 0, "tb": 0, "avg": 0.1, "obp": 0.1, "slg": 0.2, "hit_flag": 0, "hr_flag": 0}, {"player_id": 668670, "game_date": "2026-04-09", "team": "", "opponent": "", "home_away": false, "ab": 2, "hits": 0, "doubles": 0, "triples": 0, "hr": 0, "rbi": 0, "runs": 1, "bb": 0, "k": 1, "sb": 0, "tb": 0, "avg": 0.083, "obp": 0.154, "slg": 0.167, "hit_flag": 0, "hr_flag": 0}, {"player_id": 668670, "game_date": "2026-04-15", "team": "", "opponent": "", "home_away": true, "ab": 2, "hits": 0, "doubles": 0, "triples": 0, "hr": 0, "rbi": 1, "runs": 0, "bb": 0, "k": 1, "sb": 0, "tb": 0, "avg": 0.071, "obp": 0.125, "slg": 0.143, "hit_flag": 0, "hr_flag": 0}, {"player_id": 668670, "game_date": "2026-04-18", "team": "", "opponent": "", "home_away": false, "ab": 3, "hits": 1, "doubles": 1, "triples": 0, "hr": 0, "rbi": 1, "runs": 0, "bb": 0, "k": 0, "sb": 0, "tb": 2, "avg": 0.118, "obp": 0.15, "slg": 0.235, "hit_flag": 1, "hr_flag": 0}, {"player_id": 668670, "game_date": "2026-04-20", "team": "", "opponent": "", "home_away": false, "ab": 4, "hits": 1, "doubles": 0, "triples": 0, "hr": 0, "rbi": 1, "runs": 0, "bb": 0, "k": 1, "sb": 1, "tb": 1, "avg": 0.143, "obp": 0.167, "slg": 0.238, "hit_flag": 1, "hr_flag": 0}, {"player_id": 668670, "game_date": "2026-04-22", "team": "", "opponent": "", "home_away": true, "ab": 2, "hits": 0, "doubles": 0, "triples": 0, "hr": 0, "rbi": 0, "runs": 0, "bb": 1, "k": 0, "sb": 0, "tb": 0, "avg": 0.13, "obp": 0.185, "slg": 0.217, "hit_flag": 0, "hr_flag": 0}, {"player_id": 668670, "game_date": "2026-04-26", "team": "", "opponent": "", "home_away": false, "ab": 4, "hits": 1, "doubles": 0, "triples": 0, "hr": 0, "rbi": 0, "runs": 0, "bb": 0, "k": 2, "sb": 0, "tb": 1, "avg": 0.148, "obp": 0.194, "slg": 0.222, "hit_flag": 1, "hr_flag": 0}, {"player_id": 668670, "game_date": "2026-04-30", "team": "", "opponent": "", "home_away": false, "ab": 3, "hits": 0, "doubles": 0, "triples": 0, "hr": 0, "rbi": 0, "runs": 0, "bb": 0, "k": 1, "sb": 0, "tb": 0, "avg": 0.133, "obp": 0.176, "slg": 0.2, "hit_flag": 0, "hr_flag": 0}]